LICENCE.txt
MANIFEST.in
README.txt
setup.py
pn_calcy/__init__.py
pn_calcy.egg-info/PKG-INFO
pn_calcy.egg-info/SOURCES.txt
pn_calcy.egg-info/dependency_links.txt
pn_calcy.egg-info/top_level.txt