Metadata-Version: 2.1
Name: pn-calcy
Version: 0.0.1
Summary: this is a dumb package used for dumb calculation.
Home-page: 
Author: Pranav Nair
Author-email: nairpranav541@gmail.com
License: MIT
License-File: LICENCE.txt
